jeraconv/__init__.py
jeraconv/jeraconv.py
jeraconv/data/jeraconv.json
tests/__init__.py
tests/test_jeraconv.py
jeraconv-0.2.1.dist-info/LICENSE
jeraconv-0.2.1.dist-info/LICENSE_JP
jeraconv-0.2.1.dist-info/METADATA
jeraconv-0.2.1.dist-info/WHEEL
jeraconv-0.2.1.dist-info/top_level.txt
jeraconv-0.2.1.dist-info/RECORD
