Metadata-Version: 2.1
Name: jeraconv
Version: 0.2.1
Summary: jeraconv (Japanese Era Name Converter) is a converter that converts Japanese eras to West calendar.
Home-page: https://github.com/slangsoft/jeraconv
Author: slangsoft
Author-email: slangsoft@gmail.com
License: MIT
Keywords: jeraconv japanese era
Platform: UNKNOWN
Classifier: License :: OSI Approved :: MIT License
Classifier: Programming Language :: Python :: 3.7
